src/table_display_R0L3eX9/__init__.py
src/table_display_R0L3eX9/printcolor.py
src/table_display_R0L3eX9/table.py
table_display_r0l3ex-0.0.1.dist-info/METADATA
table_display_r0l3ex-0.0.1.dist-info/WHEEL
table_display_r0l3ex-0.0.1.dist-info/licenses/LICENSE
table_display_r0l3ex-0.0.1.dist-info/RECORD
